UsergeAntiSpamApi/__init__.py
UsergeAntiSpamApi/client.py
UsergeAntiSpamApi/errors.py
UsergeAntiSpamApi/types.py
UsergeAntiSpamApi-0.1.8.dist-info/LICENSE
UsergeAntiSpamApi-0.1.8.dist-info/METADATA
UsergeAntiSpamApi-0.1.8.dist-info/WHEEL
UsergeAntiSpamApi-0.1.8.dist-info/top_level.txt
UsergeAntiSpamApi-0.1.8.dist-info/RECORD
