Metadata-Version: 2.1
Name: UsergeAntiSpamApi
Version: 0.1.8
Summary: Wrapper for [Userge AntiSpam API](https://api.userge.tk)
Home-page: https://github.com/Krishna-Singhal/userge-federation
Author: Krishna-Singhal
Author-email: ylikehits3@gmail.com
License: UNKNOWN
Project-URL: Bug Tracker, https://github.com/Krishna-Singhal/userge-federation/issues
Platform: UNKNOWN
Classifier: Programming Language :: Python :: 3
Classifier: License :: OSI Approved :: GNU General Public License v3 (GPLv3)
Classifier: Operating System :: OS Independent
Requires-Python: >=3.6
License-File: LICENSE
Requires-Dist: requests
